{"indexes":[{"v":{"$numberInt":"2"},"key":{"_id":{"$numberInt":"1"}},"name":"_id_"},{"v":{"$numberInt":"2"},"key":{"id":{"$numberInt":"1"}},"name":"__primary_key__","unique":true},{"v":{"$numberInt":"2"},"key":{"bms_users_id":{"$numberInt":"1"},"bms_roles_id":{"$numberInt":"1"}},"name":"bms_user_tbl_role_id_bms_users_id_bms_roles_id_d2593747_uniq","unique":true},{"v":{"$numberInt":"2"},"key":{"bms_users_id":{"$numberInt":"1"}},"name":"bms_user_tbl_role_id_bms_users_id_04f568eb"},{"v":{"$numberInt":"2"},"key":{"bms_roles_id":{"$numberInt":"1"}},"name":"bms_user_tbl_role_id_bms_roles_id_e491e1f7"}],"uuid":"81f8f9ec7a6c45f4931f9941354d8b60","collectionName":"bms_user_tbl_role_id","type":"collection"}